{
    "content": null,
    "embeds": [
      {
        "color": 14327821,
        "image": {
          "url": "https://github.com/MinersStudios/WhoMine/blob/main/discord/img/nonrp_rules.png?raw=true"
        }
      },
      {
        "title": "Нонрп Правила :",
        "description": "`` 1. `` Читерские утилиты запрещены (миникарта разрешена)\n\n`` 2. `` Агрессия, конфликтность и клевета запрещена\n\n`` 3. `` Гриферство других игроков без их согласия запрещена\n(только в случае, если на вас поступит жалоба\n от загриференого человека)\n\n`` 4. `` Политические конфликты не должны проходить\n на сервере (Речь идет о политике из реального мира)\n\n`` 5. `` Создание мульти-аккаунтов запрещено\n\n`` 6. `` Вход на чужой аккаунт без разрешения \nвладельца запрещен\n\n`` 7. `` Запрещена передача/продажа аккаунта 3-им лицам\n\n`` 8. `` Администрация оставляет за собой право\n изменения данных правил без оповещения игроков\n\n`` 9. `` Использование багов ради своей выгоды, или против ᠌ ᠌ ᠌ ᠌ ᠌ ᠌ ᠌᠌ ᠌ ᠌ ᠌ ᠌ ᠌ ᠌\nигроков/сервера, запрещена \n\n`` 10. `` По поводу добавления в вайт-лист писать <@545925589123465226> ,\n либо <@532303680050036736>",
        "color": 14327821
      }
    ],
    "attachments": []
  }
